resemble/__init__.py
resemble/stream_decoder.py
resemble-1.7.0.dist-info/licenses/LICENSE
resemble-1.7.0.dist-info/METADATA
resemble-1.7.0.dist-info/WHEEL
resemble-1.7.0.dist-info/top_level.txt
resemble-1.7.0.dist-info/RECORD
