Metadata-Version: 2.4
Name: resemble
Version: 1.7.0
Summary: Resemble API Client Library
Home-page: https://github.com/resemble-ai/resemble-python
Author: ResembleAI
Author-email: team@resemble.ai
Project-URL: Bug Tracker, https://github.com/resemble-ai/resemble-python/issues
Classifier: Programming Language :: Python :: 3
Classifier: License :: OSI Approved :: Apache Software License
Classifier: Operating System :: OS Independent
Requires-Python: >=3.6
License-File: LICENSE
Requires-Dist: requests<3,>2
Dynamic: author
Dynamic: author-email
Dynamic: classifier
Dynamic: description
Dynamic: description-content-type
Dynamic: home-page
Dynamic: license-file
Dynamic: project-url
Dynamic: requires-dist
Dynamic: requires-python
Dynamic: summary
